python_hackrf/__init__.py
python_hackrf/__main__.py
python_hackrf/pyhackrf_tools/__init__.py
python_hackrf/pyhackrf_tools/pyhackrf_info.py
python_hackrf/pyhackrf_tools/pyhackrf_operacake.py
python_hackrf/pyhackrf_tools/pyhackrf_sweep.cpython-311-darwin.so
python_hackrf/pyhackrf_tools/pyhackrf_transfer.cpython-311-darwin.so
python_hackrf/pyhackrf_tools/utils.py
python_hackrf/pylibhackrf/__android.py
python_hackrf/pylibhackrf/__init__.py
python_hackrf/pylibhackrf/pyhackrf.cpython-311-darwin.so
python_hackrf/pylibhackrf/pyhackrf.pyi
python_hackrf-1.3.2.dist-info/licenses/LICENSE
python_hackrf-1.3.2.dist-info/METADATA
python_hackrf-1.3.2.dist-info/WHEEL
python_hackrf-1.3.2.dist-info/entry_points.txt
python_hackrf-1.3.2.dist-info/top_level.txt
python_hackrf-1.3.2.dist-info/RECORD
