Metadata-Version: 2.4
Name: python_hackrf
Version: 1.3.2
Summary: This is a wrapper for hackrf. It includes both libhackrf and hackrf-tools
Author-email: Leonid Gvozdev <leo.gvozdev.dev@gmail.com>
Project-URL: Homepage, https://github.com/GvozdevLeonid/python_hackrf
Project-URL: Bug Tracker, https://github.com/GvozdevLeonid/python_hackrf/issues
Classifier: License :: OSI Approved :: MIT License
Classifier: Programming Language :: Python :: 3
Classifier: Operating System :: Android
Classifier: Operating System :: POSIX :: Linux
Classifier: Operating System :: MacOS
Classifier: Operating System :: MacOS :: MacOS X
Classifier: Operating System :: Microsoft :: Windows
Requires-Python: >=3.9
License-File: LICENSE
Requires-Dist: numpy
Dynamic: license-file
